livekit_ai_note_taker/__init__.py
livekit_ai_note_taker/agent.py
livekit_ai_note_taker/config.py
livekit_ai_note_taker/runner.py
livekit_ai_note_taker-0.1.8.dist-info/METADATA
livekit_ai_note_taker-0.1.8.dist-info/WHEEL
livekit_ai_note_taker-0.1.8.dist-info/entry_points.txt
livekit_ai_note_taker-0.1.8.dist-info/top_level.txt
livekit_ai_note_taker-0.1.8.dist-info/RECORD
