Metadata-Version: 2.4
Name: livekit-ai-note-taker
Version: 0.1.8
Summary: AI note taker for LiveKit that listens to meeting audio, transcribes with Deepgram,AWS and streams concise summaries via Groq/OpenRouter(ollama)/OpenAI.
Author: Oladunjoye Abiola Moses
License: Proprietary
Project-URL: Homepage, https://github.com/abiola814/Livekit-AI-note-taker
Project-URL: Issues, https://github.com/abiola814/Livekit-AI-note-taker/issues
Requires-Python: >=3.9
Requires-Dist: livekit==1.0.19
Requires-Dist: livekit-agents==1.3.2
Requires-Dist: livekit-api==1.0.7
Requires-Dist: livekit-blingfire==1.0.0
Requires-Dist: livekit-plugins-deepgram==1.3.2
Requires-Dist: livekit-plugins-openai==1.3.2
Requires-Dist: livekit-protocol==1.1.0
Requires-Dist: opentelemetry-api<1.39,>=1.34.1
Requires-Dist: opentelemetry-sdk<1.39,>=1.34.1
Requires-Dist: opentelemetry-exporter-otlp-proto-http<1.39,>=1.34.1
Requires-Dist: opentelemetry-exporter-otlp-proto-grpc<1.39,>=1.34.1
Requires-Dist: aiohttp>=3.9
Requires-Dist: python-dotenv>=1.0
Requires-Dist: groq>=0.6
Requires-Dist: httpx>=0.27
Requires-Dist: requests>=2.31
